{
  "id": "62afa4b5-44b4-49bd-aa62-8a09bbf34b91",
  "name": "language",
  "nodes": [
    {
      "note": "",
      "feature": "trace",
      "x": 696,
      "name": "Trace",
      "y": 180,
      "id": "87d9df26-981b-46c5-89b8-0d393e0b9a48",
      "category": "dev",
      "params": {
        "msg": {
          "type": "textareaMentions",
          "value": "Hello"
        },
        "level": {
          "type": "choice",
          "value": "info"
        }
      },
      "featureVersion": "2.2",
      "connections": [
        {
          "inputId": "input",
          "outputId": "done",
          "targetNodeId": "8965a8d5-685a-4269-924b-02ce6f57818c"
        }
      ]
    },
    {
      "note": "",
      "feature": "end",
      "x": 1068,
      "name": "Fin",
      "y": 1128,
      "id": "a46ec51a-5cc4-4683-9c22-a8ecc0108fa6",
      "category": "dev",
      "params": {},
      "featureVersion": "1.1",
      "connections": []
    },
    {
      "note": "",
      "feature": "onHttp",
      "x": 636,
      "name": "HTTP Entrant",
      "y": 36,
      "id": "31c20efe-5974-4975-9824-56292dbf36c3",
      "category": "http",
      "params": {
        "response_timeout": {
          "type": "int",
          "value": 60
        },
        "variables": {
          "type": "VariablesList",
          "value": [
            {
              "name": "body",
              "parameter": "body",
              "displayed": true,
              "editable": true,
              "originEditable": false,
              "nameEditable": true,
              "parameterEditable": false,
              "removable": false,
              "type": "object"
            },
            {
              "name": "clientip",
              "parameter": "ip",
              "displayed": true,
              "editable": true,
              "originEditable": false,
              "nameEditable": true,
              "parameterEditable": false,
              "removable": false,
              "type": "string"
            }
          ]
        },
        "immediate_response": {
          "type": "bool",
          "value": true
        },
        "method": {
          "type": "choice",
          "value": "GET"
        },
        "securityComment": {
          "type": "comment",
          "value": null
        },
        "url": {
          "type": "textMentions",
          "value": "/api/flows/test"
        },
        "token": {
          "type": "token",
          "value": null
        }
      },
      "featureVersion": "2.8",
      "connections": [
        {
          "inputId": "input",
          "outputId": "request",
          "targetNodeId": "87d9df26-981b-46c5-89b8-0d393e0b9a48"
        },
        {
          "inputId": "input",
          "outputId": "err",
          "targetNodeId": "87d9df26-981b-46c5-89b8-0d393e0b9a48"
        }
      ]
    },
    {
      "note": "",
      "feature": "makeCall",
      "x": 780,
      "name": "Appeler",
      "y": 324,
      "id": "8965a8d5-685a-4269-924b-02ce6f57818c",
      "category": "softcmp",
      "params": {
        "phoneDisplay": {
          "type": "phoneDisplay",
          "value": null
        },
        "number": {
          "type": "phoneNumber",
          "value": "1500"
        },
        "variables": {
          "type": "VariablesList",
          "value": [
            {
              "displayed": false,
              "parameter": "callingNumber",
              "name": "callingNumber",
              "type": "string"
            },
            {
              "displayed": false,
              "parameter": "calledNumber",
              "name": "calledNumber",
              "type": "string"
            },
            {
              "displayed": false,
              "editable": false,
              "parameter": "abcfMessageRef",
              "name": "abcfMessageRef",
              "type": "string"
            },
            {
              "displayed": false,
              "editable": false,
              "parameter": "error",
              "name": "error",
              "type": "string"
            },
            {
              "displayed": false,
              "editable": false,
              "parameter": "callRef",
              "name": "callReference",
              "type": "string"
            }
          ]
        },
        "correlatorData": {
          "type": "phoneDisplay",
          "value": ""
        },
        "callingNumber": {
          "type": "phoneNumber",
          "value": "1501"
        },
        "ringingTimer": {
          "type": "numberOrVarFormat",
          "value": 30
        }
      },
      "featureVersion": "1.8",
      "connections": [
        {
          "inputId": "input",
          "outputId": "makeCallFailed",
          "targetNodeId": "fd5d70d2-1da0-4b5f-a930-4ba20982cabc"
        },
        {
          "inputId": "input",
          "outputId": "makeCallDone",
          "targetNodeId": "a9736cb3-4b32-401f-8520-30bdea38d25a"
        }
      ]
    },
    {
      "note": "",
      "feature": "end",
      "x": 1056,
      "name": "Fin error",
      "y": 624,
      "id": "fd5d70d2-1da0-4b5f-a930-4ba20982cabc",
      "category": "dev",
      "params": {},
      "featureVersion": "1.1",
      "connections": []
    },
    {
      "note": "",
      "feature": "releaseCall",
      "x": 144,
      "name": "Libération",
      "y": 1140,
      "id": "fb7ff83d-db50-47e1-9616-9c41197a9202",
      "category": "softcmp",
      "params": {},
      "featureVersion": "1.1",
      "connections": [
        {
          "inputId": "input",
          "outputId": "releaseEnded",
          "targetNodeId": "a46ec51a-5cc4-4683-9c22-a8ecc0108fa6"
        },
        {
          "inputId": "input",
          "outputId": "releaseEnded",
          "targetNodeId": "a46ec51a-5cc4-4683-9c22-a8ecc0108fa6"
        }
      ]
    },
    {
      "note": "",
      "feature": "announcement",
      "x": 372,
      "name": "Annonce",
      "y": 816,
      "id": "de80dbe5-b973-41e7-a72f-eb3178f0579d",
      "category": "softcmp",
      "params": {
        "file": {
          "type": "prompt",
          "value": "a8ee3cd9-fad1-482e-9dad-ec351d54995d"
        },
        "bargein": {
          "type": "bool",
          "value": true
        },
        "timeout": {
          "type": "int",
          "value": 0
        }
      },
      "featureVersion": "2.7",
      "connections": [
        {
          "inputId": "input",
          "outputId": "callReleased",
          "targetNodeId": "a46ec51a-5cc4-4683-9c22-a8ecc0108fa6"
        },
        {
          "inputId": "input",
          "outputId": "ok",
          "targetNodeId": "fb7ff83d-db50-47e1-9616-9c41197a9202"
        }
      ]
    },
    {
      "note": "",
      "feature": "tts",
      "x": 120,
      "name": "Synthèse vocale",
      "y": 552,
      "id": "8e9e009c-cbb7-4906-9721-82089dfec8f0",
      "category": "dev",
      "params": {
        "tts": {
          "type": "tts-enabled",
          "value": {
            "ttsText": "Maître Corbeau, sur un arbre perché,\nTenait en son bec un fromage.\nMaître Renard, par l'odeur alléché,\nLui tint à peu près ce langage :\nEt bonjour, Monsieur du Corbeau.\nQue vous êtes joli ! que vous me semblez beau !\nSans mentir, si votre ramage\nSe rapporte à votre plumage,\nVous êtes le Phénix",
            "ttsConfigurationId": "f1921b91-0149-4dc2-a2b3-8d9e3a719fbf",
            "ttstext": ""
          }
        },
        "variables": {
          "type": "VariablesList",
          "value": [
            {
              "displayed": true,
              "nameEditable": true,
              "originEditable": false,
              "mandatoryEditable": false,
              "removable": false,
              "parameter": "prompt",
              "name": "prompt",
              "typeEditable": false,
              "multiple": false,
              "parameterEditable": false,
              "type": "file",
              "mandatory": true
            }
          ]
        }
      },
      "featureVersion": "1.0",
      "connections": [
        {
          "inputId": "input",
          "outputId": "ok",
          "targetNodeId": "de80dbe5-b973-41e7-a72f-eb3178f0579d"
        }
      ]
    },
    {
      "note": "",
      "feature": "language",
      "x": 624,
      "name": "Langue",
      "y": 660,
      "id": "a9736cb3-4b32-401f-8520-30bdea38d25a",
      "category": "dev",
      "params": {
        "language": {
          "type": "language",
          "value": "fr-FR"
        }
      },
      "featureVersion": "1.0",
      "connections": [
        {
          "inputId": "input",
          "outputId": "next",
          "targetNodeId": "de80dbe5-b973-41e7-a72f-eb3178f0579d"
        }
      ]
    }
  ],
  "globalVariables": []
}